nicegui_pdf/__init__.py
nicegui_pdf/pdf_viewer.js
nicegui_pdf/pdf_viewer.py
nicegui_pdf/pdf_js/jquery.min.js
nicegui_pdf/pdf_js/pdf.min.js
nicegui_pdf/pdf_js/pdf.worker.min.js
nicegui_pdf/pdf_js/pdf_viewer.min.css
nicegui_pdf-0.0.7.dist-info/METADATA
nicegui_pdf-0.0.7.dist-info/WHEEL
nicegui_pdf-0.0.7.dist-info/licenses/LICENSE
nicegui_pdf-0.0.7.dist-info/RECORD
