Metadata-Version: 2.4
Name: nicegui-pdf
Version: 0.0.7
Summary: A PDF viewer for nicegui based on pdf.js
Project-URL: Repository, https://github.com/peerdavid/nicegui-pdf
Project-URL: Issues, https://github.com/peerdavid/nicegui-pdf/issues
Author-email: David Peer <david.peer@outlook.com>
License-Expression: MIT
License-File: LICENSE
Requires-Python: >=3.12
Requires-Dist: nicegui>=2.14.1
